{
  "annotations": {
    "list": [
      {
        "builtIn": 1,
        "datasource": {
          "type": "grafana",
          "uid": "-- Grafana --"
        },
        "enable": true,
        "hide": true,
        "iconColor": "rgba(0, 211, 255, 1)",
        "name": "Annotations & Alerts",
        "type": "dashboard"
      }
    ]
  },
  "editable": true,
  "fiscalYearStartMonth": 0,
  "graphTooltip": 0,
  "id": 2,
  "links": [],
  "liveNow": false,
  "panels": [
    {
      "datasource": {
        "default": true,
        "type": "prometheus",
        "uid": "P1809F7CD0C75ACF3"
      },
      "fieldConfig": {
        "defaults": {
          "color": {
            "mode": "thresholds"
          },
          "displayName": "GPU#${__field.labels.deviceId}",
          "mappings": [],
          "max": 105,
          "thresholds": {
            "mode": "absolute",
            "steps": [
              {
                "color": "green",
                "value": null
              },
              {
                "color": "red",
                "value": 99
              }
            ]
          },
          "unit": "percent"
        },
        "overrides": []
      },
      "gridPos": {
        "h": 26,
        "w": 24,
        "x": 0,
        "y": 0
      },
      "id": 1,
      "maxPerRow": 4,
      "options": {
        "minVizHeight": 75,
        "minVizWidth": 75,
        "orientation": "auto",
        "reduceOptions": {
          "calcs": [
            "lastNotNull"
          ],
          "fields": "",
          "values": false
        },
        "showThresholdLabels": false,
        "showThresholdMarkers": true,
        "sizing": "auto"
      },
      "pluginVersion": "11.2.2+security-01",
      "repeat": "servers",
      "repeatDirection": "h",
      "targets": [
        {
          "datasource": {
            "type": "prometheus",
            "uid": "P1809F7CD0C75ACF3"
          },
          "disableTextWrap": false,
          "editorMode": "builder",
          "expr": "mx_gpu_usage{Hostname=\"$servers\"}",
          "fullMetaSearch": false,
          "includeNullMetadata": true,
          "instant": false,
          "range": true,
          "refId": "A",
          "useBackend": false
        }
      ],
      "title": "$servers",
      "type": "gauge"
    }
  ],
  "refresh": "5s",
  "schemaVersion": 39,
  "tags": [],
  "templating": {
    "list": [
      {
        "current": {
          "selected": true,
          "text": "lg-pc-10-2-122-120",
          "value": "lg-pc-10-2-122-120"
        },
        "datasource": {
          "type": "prometheus",
          "uid": "P1809F7CD0C75ACF3"
        },
        "definition": "label_values({job=\"metax-mx-exporter\"},Hostname)",
        "hide": 0,
        "includeAll": false,
        "multi": false,
        "name": "servers",
        "options": [],
        "query": {
          "qryType": 1,
          "query": "label_values({job=\"metax-mx-exporter\"},Hostname)",
          "refId": "PrometheusVariableQueryEditor-VariableQuery"
        },
        "refresh": 1,
        "regex": "",
        "skipUrlSync": false,
        "sort": 0,
        "type": "query"
      }
    ]
  },
  "time": {
    "from": "now-15m",
    "to": "now"
  },
  "timepicker": {},
  "timezone": "browser",
  "title": "MetaX Data Center GPU Usage Overview",
  "uid": "ddgekzn5ueneoa",
  "version": 3,
  "weekStart": ""
}